Workbook

Sheet スマホ
A1: ② スマホで見る：家計・積立
A2: ■ 現在地
A3: 現在の積立残高 | B3: =ボード!B5 -> 118000
A4: 目標 | B4: =ボード!B6 -> 1000000
A5: 進み具合 | B5: =ボード!B7 -> 0.118
A6: 計画と比べて | B6: =ボード!B8 -> 計画より遅れ
A7: 目標に必要な毎月の積立額（更新後） | B7: =ボード!B10 -> 32624.281
A8: 今の積立額を続けた場合の期限時点（仮定） | B8: =ボード!B12 -> 988088.72
A9: 入力のチェック | B9: =ボード!B13 -> OK
A10: 単位：円。仮定の利回りによる計算で、予測・保証ではありません。元本割れのリスクがあります。税金は含みません。
A26: ■ 毎月の数字を入れる：月末の積立残高（円）
A27: 1か月目 | B27: 30500
A28: 2か月目 | B28: 61000
A29: 3か月目 | B29: 90000
A30: 4か月目 | B30: 118000
A31: 5か月目
A32: 6か月目
A33: 7か月目
A34: 8か月目
A35: 9か月目
A36: 10か月目
A37: 11か月目
A38: 12か月目
A39: 13か月目
A40: 14か月目
A41: 15か月目
A42: 16か月目
... A56: 30か月目

Sheet 使い方
A1: ② 現在地ボード：家計・積立
A3: 毎月1回、「スマホ」シートの下にある「毎月の数字を入れる」欄に、月末の積立残高（評価額のおおよその額）を入れてください。
A4: 入れると、現在地・目標までの進み具合と、期限までに目標に届くために必要な毎月の積立額が自動で計算され、残りの月の予定が作り直されます。
A5: 利回りは仮定です（予測・保証ではありません）。0%やマイナスでも試してください。税金（課税口座は利益に原則20.315%）は含みません。銘柄や商品の選び方の助言は含みません。
A7: 凡例
A8: 黄色のセル（青字）＝あなたが入力する欄
A9: 緑のセル＝自動で計算される「現在地」と「これからの予定」
A10: その他の白いセル＝自動計算（触らない）
A11: 入っている数字は架空の記入例です。上書きしてお使いください。
A13: このシートは、入力した数字から機械的に計算した目安です。結果を保証するものではありません。氏名・口座番号・ID・パスワード・学校名などは書かないでください。

Sheet 前提
A1: 前提（仮定条件）
A2: 最初の積立残高（円） | B2: 0
A3: 目標の積立残高（円） | B3: 1000000
A4: 期限までの月数 | B4: 30
A5: 仮定の利回り（年） | B5: 0.03
A6: 運用手数料（年） | B6: 0.001
A7: 月あたりの実質利回り（自動） | B7: =(B5-B6)/12 -> 0.0024166667
A8: 当初の計画の毎月の積立額（自動・円） | B8: =IF(B7=0,(B3-B2)/B4,PMT(B7,B4,B2,-B3)) -> 32179.843

Sheet 記録
A1: 月 | B1: 当初の計画（円・仮定） | C1: 実績（円）※スマホのシートから自動 | D1: 更新後の予定（円・仮定）
A2: 1 | B2: =IF(前提!$B$7=0,前提!$B$2+前提!$B$8*A2,FV(前提!$B$7,A2,-前提!$B$8,-前提!$B$2)) -> 32179.843 | C2: =IF(スマホ!B27="","",スマホ!B27) -> 30500 | D2: =IFERROR(IF(OR(ボード!$B$4="",ボード!$B$10="",A2<=ボード!$B$4),"",IF(前提!$B$7=0,ボード!$B$5+ボード!$B$10*(A2-ボード!$B$4),FV(前提!$B$7,A2-ボード!$B$4,-ボード!$B$10,-ボード!$B$5))),"")
A3: 2 | B3: =IF(前提!$B$7=0,前提!$B$2+前提!$B$8*A3,FV(前提!$B$7,A3,-前提!$B$8,-前提!$B$2)) -> 64437.455 | C3: =IF(スマホ!B28="","",スマホ!B28) -> 61000 | D3: =IFERROR(IF(OR(ボード!$B$4="",ボード!$B$10="",A3<=ボード!$B$4),"",IF(前提!$B$7=0,ボード!$B$5+ボード!$B$10*(A3-ボード!$B$4),FV(前提!$B$7,A3-ボード!$B$4,-ボード!$B$10,-ボード!$B$5))),"")
A4: 3 | B4: =IF(前提!$B$7=0,前提!$B$2+前提!$B$8*A4,FV(前提!$B$7,A4,-前提!$B$8,-前提!$B$2)) -> 96773.022 | C4: =IF(スマホ!B29="","",スマホ!B29) -> 90000 | D4: =IFERROR(IF(OR(ボード!$B$4="",ボード!$B$10="",A4<=ボード!$B$4),"",IF(前提!$B$7=0,ボード!$B$5+ボード!$B$10*(A4-ボード!$B$4),FV(前提!$B$7,A4-ボード!$B$4,-ボード!$B$10,-ボード!$B$5))),"")
A5: 4 | B5: =IF(前提!$B$7=0,前提!$B$2+前提!$B$8*A5,FV(前提!$B$7,A5,-前提!$B$8,-前提!$B$2)) -> 129186.73 | C5: =IF(スマホ!B30="","",スマホ!B30) -> 118000 | D5: =IFERROR(IF(OR(ボード!$B$4="",ボード!$B$10="",A5<=ボード!$B$4),"",IF(前提!$B$7=0,ボード!$B$5+ボード!$B$10*(A5-ボード!$B$4),FV(前提!$B$7,A5-ボード!$B$4,-ボード!$B$10,-ボード!$B$5))),"")
A6: 5 | B6: =IF(前提!$B$7=0,前提!$B$2+前提!$B$8*A6,FV(前提!$B$7,A6,-前提!$B$8,-前提!$B$2)) -> 161678.78 | C6: =IF(スマホ!B31="","",スマホ!B31) | D6: =IFERROR(IF(OR(ボード!$B$4="",ボード!$B$10="",A6<=ボード!$B$4),"",IF(前提!$B$7=0,ボード!$B$5+ボード!$B$10*(A6-ボード!$B$4),FV(前提!$B$7,A6-ボード!$B$4,-ボード!$B$10,-ボード!$B$5))),"") -> 150909.45
A7: 6 | B7: =IF(前提!$B$7=0,前提!$B$2+前提!$B$8*A7,FV(前提!$B$7,A7,-前提!$B$8,-前提!$B$2)) -> 194249.35 | C7: =IF(スマホ!B32="","",スマホ!B32) | D7: =IFERROR(IF(OR(ボード!$B$4="",ボード!$B$10="",A7<=ボード!$B$4),"",IF(前提!$B$7=0,ボード!$B$5+ボード!$B$10*(A7-ボード!$B$4),FV(前提!$B$7,A7-ボード!$B$4,-ボード!$B$10,-ボード!$B$5))),"") -> 183898.43
A8: 7 | B8: =IF(前提!$B$7=0,前提!$B$2+前提!$B$8*A8,FV(前提!$B$7,A8,-前提!$B$8,-前提!$B$2)) -> 226898.62 | C8: =IF(スマホ!B33="","",スマホ!B33) | D8: =IFERROR(IF(OR(ボード!$B$4="",ボード!$B$10="",A8<=ボード!$B$4),"",IF(前提!$B$7=0,ボード!$B$5+ボード!$B$10*(A8-ボード!$B$4),FV(前提!$B$7,A8-ボード!$B$4,-ボード!$B$10,-ボード!$B$5))),"") -> 216967.13
A9: 8 | B9: =IF(前提!$B$7=0,前提!$B$2+前提!$B$8*A9,FV(前提!$B$7,A9,-前提!$B$8,-前提!$B$2)) -> 259626.81 | C9: =IF(スマホ!B34="","",スマホ!B34) | D9: =IFERROR(IF(OR(ボード!$B$4="",ボード!$B$10="",A9<=ボード!$B$4),"",IF(前提!$B$7=0,ボード!$B$5+ボード!$B$10*(A9-ボード!$B$4),FV(前提!$B$7,A9-ボード!$B$4,-ボード!$B$10,-ボード!$B$5))),"") -> 250115.75
A10: 9 | B10: =IF(前提!$B$7=0,前提!$B$2+前提!$B$8*A10,FV(前提!$B$7,A10,-前提!$B$8,-前提!$B$2)) -> 292434.08 | C10: =IF(スマホ!B35="","",スマホ!B35) | D10: =IFERROR(IF(OR(ボード!$B$4="",ボード!$B$10="",A10<=ボード!$B$4),"",IF(前提!$B$7=0,ボード!$B$5+ボード!$B$10*(A10-ボード!$B$4),FV(前提!$B$7,A10-ボード!$B$4,-ボード!$B$10,-ボード!$B$5))),"") -> 283344.47
A11: 10 | B11: =IF(前提!$B$7=0,前提!$B$2+前提!$B$8*A11,FV(前提!$B$7,A11,-前提!$B$8,-前提!$B$2)) -> 325320.64 | C11: =IF(スマホ!B36="","",スマホ!B36) | D11: =IFERROR(IF(OR(ボード!$B$4="",ボード!$B$10="",A11<=ボード!$B$4),"",IF(前提!$B$7=0,ボード!$B$5+ボード!$B$10*(A11-ボード!$B$4),FV(前提!$B$7,A11-ボード!$B$4,-ボード!$B$10,-ボード!$B$5))),"") -> 316653.5
A12: 11 | B12: =IF(前提!$B$7=0,前提!$B$2+前提!$B$8*A12,FV(前提!$B$7,A12,-前提!$B$8,-前提!$B$2)) -> 358286.68 | C12: =IF(スマホ!B37="","",スマホ!B37) | D12: =IFERROR(IF(OR(ボード!$B$4="",ボード!$B$10="",A12<=ボード!$B$4),"",IF(前提!$B$7=0,ボード!$B$5+ボード!$B$10*(A12-ボード!$B$4),FV(前提!$B$7,A12-ボード!$B$4,-ボード!$B$10,-ボード!$B$5))),"") -> 350043.03
A13: 12 | B13: =IF(前提!$B$7=0,前提!$B$2+前提!$B$8*A13,FV(前提!$B$7,A13,-前提!$B$8,-前提!$B$2)) -> 391332.38 | C13: =IF(スマホ!B38="","",スマホ!B38) | D13: =IFERROR(IF(OR(ボード!$B$4="",ボード!$B$10="",A13<=ボード!$B$4),"",IF(前提!$B$7=0,ボード!$B$5+ボード!$B$10*(A13-ボード!$B$4),FV(前提!$B$7,A13-ボード!$B$4,-ボード!$B$10,-ボード!$B$5))),"") -> 383513.25
... A31: 30 | B31: =IF(前提!$B$7=0,前提!$B$2+前提!$B$8*A31,FV(前提!$B$7,A31,-前提!$B$8,-前提!$B$2)) -> 1000000 | C31: =IF(スマホ!B56="","",スマホ!B56) | D31: =IFERROR(IF(OR(ボード!$B$4="",ボード!$B$10="",A31<=ボード!$B$4),"",IF(前提!$B$7=0,ボード!$B$5+ボード!$B$10*(A31-ボード!$B$4),FV(前提!$B$7,A31-ボード!$B$4,-ボード!$B$10,-ボード!$B$5))),"") -> 1000000
A33: ※ 実績は「スマホ」シートで入力します（この列は自動）。

Sheet ボード
A1: 現在地ボード：家計・積立（仮定条件にもとづく試算）
A3: 現在地
A4: 最後に実績を入れた月 | B4: =IF(COUNT(記録!C2:C31)=0,"",LOOKUP(2,1/(記録!C2:C31<>""),記録!A2:A31)) -> 4
A5: 現在の積立残高（円） | B5: =IF(B4="","",LOOKUP(2,1/(記録!C2:C31<>""),記録!C2:C31)) -> 118000
A6: 目標（円） | B6: =前提!B3 -> 1000000
A7: 目標までの進み具合 | B7: =IF(OR(B4="",前提!B3=前提!B2),"",(B5-前提!B2)/(前提!B3-前提!B2)) -> 0.118
A8: 当初の計画と比べて | B8: =IF(B4="","",IF(B5>=INDEX(記録!B2:B31,B4),"計画どおり、または先行","計画より遅れ")) -> 計画より遅れ
A9: 残りの月数 | B9: =IF(B4="","",前提!B4-B4) -> 26
A10: 目標に届くために必要な毎月の積立額（更新後・円） | B10: =IF(B4="","",IF(B5>=前提!B3,0,IF(B9<=0,"",IF(前提!B7=0,(前提!B3-B5)/B9,PMT(前提!B7,B9,B5,-前提!B3))))) -> 32624.281
A11: 当初の計画の毎月の積立額（円） | B11: =前提!B8 -> 32179.843
A12: 当初の積立額を続けた場合の期限時点の残高（円・仮定） | B12: =IF(B4="","",IF(B9<=0,B5,IF(前提!B7=0,B5+前提!B8*B9,FV(前提!B7,B9,-前提!B8,-B5)))) -> 988088.72
A13: 入力のチェック | B13: =IF(COUNTIF(記録!C2:C31,"<0")>0,"マイナスの値があります。確認してください",IF(B4="","実績を入力してください",IF(B9<=0,"期限に達しました（前提の見直しが必要）",IF(COUNT(記録!C2:C31)<B4,"入力していない月があります（現在地は最後に入力した月で計算）","OK")))) -> OK
A15: 計算の前提：月あたりの利回り＝（年の利回り−年の運用手数料）÷12。最初の残高は1か月目の初めにあり、毎月の積立は月末に入る。複利は月ごと。税金・物価上昇は含まない。
A16: ※ 仮定の利回りによる機械的な計算で、予測・保証ではありません。投資には元本割れのリスクがあります。
